pyiomica/__init__.py
pyiomica/categorizationFunctions.py
pyiomica/clusteringFunctions.py
pyiomica/coreFunctions.py
pyiomica/dataStorage.py
pyiomica/enrichmentAnalyses.py
pyiomica/extendedDataFrame.py
pyiomica/frequencySubjectMatch.py
pyiomica/globalVariables.py
pyiomica/utilityFunctions.py
pyiomica/visibilityGraphAuxiliaryFunctions.py
pyiomica/visibilityGraphCommunityDetection.py
pyiomica/visualizationFunctions.py
pyiomica/data/MathIOmicaMassDictionary.csv
pyiomica/data/MathIOmicaMolecularDictionary.csv
pyiomica/data/PyIOmica.png
pyiomica/data/PyIOmicaMassDictionary.json.gz
pyiomica/data/PyIOmicaMolecularDictionary.json.gz
pyiomica/data/__init__.py
pyiomica/data/goBasicObo.txt.gz
pyiomica/data/humanGeneOntAssoc.json.gz
pyiomica/data/humanGeneUCSCTable.json.gz
pyiomica/data/humanIdentifierAssoc.json.gz
pyiomica/data/pathway__KEGGDictionary.json.gz
pyiomica/data/pathway_cpdKEGGMemberToPathAssociation.json.gz
pyiomica/data/pathway_cpdKEGGPathToMemberAssociation.json.gz
pyiomica/data/pathway_hsaKEGGMemberToPathAssociation.json.gz
pyiomica/data/pathway_hsaKEGGPathToMemberAssociation.json.gz
pyiomica/data/pathway_hsa_KEGGDictionary.json.gz
pyiomica/data/ExampleData/SLV.zip
pyiomica/data/ExampleData/exampleClusteringObject_SLV_Delta_LAG1_Autocorr.pklz
pyiomica/data/ExampleData/MathIOmicaExamples/metabolomicsNegativeModeExample
pyiomica/data/ExampleData/MathIOmicaExamples/metabolomicsPositiveModeExample
pyiomica/data/ExampleData/MathIOmicaExamples/proteinClassificationExample
pyiomica/data/ExampleData/MathIOmicaExamples/proteinExample
pyiomica/data/ExampleData/MathIOmicaExamples/proteinTimeSeriesExample
pyiomica/data/ExampleData/MathIOmicaExamples/rnaExample
pyiomica-1.4.1.dist-info/licenses/LICENSE
pyiomica_LICENSES/GOConsortiumLicensing.txt
pyiomica_LICENSES/HUPO_PSIFiles.txt
pyiomica_LICENSES/KEGGLicensing.txt
pyiomica_LICENSES/LICENSE
pyiomica_LICENSES/NCBILicensing.txt
pyiomica_LICENSES/UCSCBrowserLicensing.txt
pyiomica_LICENSES/__init__.py
pyiomica-1.4.1.dist-info/METADATA
pyiomica-1.4.1.dist-info/WHEEL
pyiomica-1.4.1.dist-info/top_level.txt
pyiomica-1.4.1.dist-info/RECORD
