Metadata-Version: 2.4
Name: pyiomica
Version: 1.4.1
Summary: Omics Analysis Tool Suite
Home-page: https://github.com/gmiaslab/pyiomica
Download-URL: https://github.com/gmiaslab/pyiomica/archive/1.4.1.tar.gz
Author: S. Domanskyi, C. Piermarocchi, G. Mias
Author-email: gmiaslab@gmail.com
License: MIT
Keywords: omics,longitudinal,bioinformatics
Classifier: License :: OSI Approved :: MIT License
Classifier: Programming Language :: Python :: 3
Classifier: Topic :: Scientific/Engineering :: Bio-Informatics
Classifier: Intended Audience :: Science/Research
Classifier: Intended Audience :: Education
Classifier: Intended Audience :: Developers
Classifier: Intended Audience :: End Users/Desktop
Classifier: Operating System :: MacOS
Classifier: Operating System :: Microsoft :: Windows
Classifier: Operating System :: Unix
Classifier: Topic :: Education
Classifier: Topic :: Utilities
License-File: LICENSE
Requires-Dist: appdirs>=1.4.4
Requires-Dist: h5py>=3.14.0
Requires-Dist: matplotlib>=3.10.3
Requires-Dist: networkx>=3.5
Requires-Dist: numba>=0.61.2
Requires-Dist: numpy>=2.2.6
Requires-Dist: openpyxl>=3.1.5
Requires-Dist: pandas>=2.3.0
Requires-Dist: pymysql>=1.1.1
Requires-Dist: requests>=2.32.4
Requires-Dist: scikit-learn>=1.7.0
Requires-Dist: scipy>=1.15.3
Requires-Dist: tables>=3.10.2
Requires-Dist: xlsxwriter>=3.2.5
Dynamic: author
Dynamic: author-email
Dynamic: classifier
Dynamic: description
Dynamic: description-content-type
Dynamic: download-url
Dynamic: home-page
Dynamic: keywords
Dynamic: license
Dynamic: license-file
Dynamic: requires-dist
Dynamic: summary
